{"id":6224,"name":"isClusterAdmin","kind":64,"kindString":"Function","flags":{},"children":[],"sources":[{"fileName":"src/users.ts","fullFileName":"/home/runner/work/FAIMS3/FAIMS3/src/users.ts","line":367,"character":22,"url":"https://github.com/FAIMS/FAIMS3/blob/a300d3b/src/users.ts#L367"}],"signatures":[{"id":6225,"name":"isClusterAdmin","kind":4096,"kindString":"Call signature","flags":{},"parameters":[{"id":6226,"name":"cluster_id","kind":32768,"kindString":"Parameter","flags":{},"type":{"type":"intrinsic","name":"string"},"text":{}}],"type":{"type":"reference","typeArguments":[{"type":"intrinsic","name":"boolean"}],"name":"Promise","qualifiedName":"Promise","package":"typescript"},"is":{"declaration":false},"location":{"query":"users.Function.isClusterAdmin","hash":"isClusterAdmin"},"text":{},"sources":[{"fileName":"src/users.ts","fullFileName":"/home/runner/work/FAIMS3/FAIMS3/src/users.ts","line":367,"character":0,"url":"https://github.com/FAIMS/FAIMS3/blob/a300d3b/src/users.ts#L367"}],"parentId":6224}],"is":{"declaration":true},"location":{"query":"users.Function.isClusterAdmin","hash":""},"text":{},"parentId":6182}
