{"id":11,"name":"DIRECTORY_AUTH","kind":32,"kindString":"Variable","flags":{"isConst":true},"children":[],"sources":[{"fileName":"src/buildconfig.ts","fullFileName":"/home/brian/FAIMS/3/FAIMS3/src/buildconfig.ts","line":296,"character":13,"url":"https://github.com/FAIMS/FAIMS3/blob/1c1db95f/src/buildconfig.ts#L296"}],"type":{"type":"union","types":[{"type":"intrinsic","name":"undefined"},{"type":"reflection","declaration":{"id":12,"name":"__type","kind":65536,"kindString":"Type literal","flags":{},"children":[{"id":14,"name":"password","kind":1024,"kindString":"Property","flags":{},"sources":[{"fileName":"src/buildconfig.ts","line":220,"character":58,"url":"https://github.com/FAIMS/FAIMS3/blob/1c1db95f/src/buildconfig.ts#L220"}],"type":{"type":"intrinsic","name":"string"}},{"id":13,"name":"username","kind":1024,"kindString":"Property","flags":{},"sources":[{"fileName":"src/buildconfig.ts","line":220,"character":40,"url":"https://github.com/FAIMS/FAIMS3/blob/1c1db95f/src/buildconfig.ts#L220"}],"type":{"type":"intrinsic","name":"string"}}],"groups":[{"title":"Properties","children":[14,13]}],"sources":[{"fileName":"src/buildconfig.ts","line":220,"character":39,"url":"https://github.com/FAIMS/FAIMS3/blob/1c1db95f/src/buildconfig.ts#L220"}]}}]},"defaultValue":"...","is":{"declaration":true},"location":{"query":"buildconfig.Variable.DIRECTORY_AUTH","hash":""},"text":{},"parentId":4}
