{"id":5299,"name":"logError","kind":64,"kindString":"Function","flags":{},"children":[],"sources":[{"fileName":"src/logging.tsx","fullFileName":"/home/brian/FAIMS/3/FAIMS3/src/logging.tsx","line":123,"character":13,"url":"https://github.com/FAIMS/FAIMS3/blob/766d1cb2/src/logging.tsx#L123"}],"signatures":[{"id":5300,"name":"logError","kind":4096,"kindString":"Call signature","flags":{},"parameters":[{"id":5301,"name":"error","kind":32768,"kindString":"Parameter","flags":{},"type":{"type":"intrinsic","name":"any"},"text":{}}],"type":{"type":"intrinsic","name":"void"},"is":{"declaration":false},"location":{"query":"logging.Function.logError","hash":"logError"},"text":{},"sources":[{"fileName":"src/logging.tsx","fullFileName":"/home/brian/FAIMS/3/FAIMS3/src/logging.tsx","line":123,"character":24,"url":"https://github.com/FAIMS/FAIMS3/blob/766d1cb2/src/logging.tsx#L123"}],"parentId":5299}],"is":{"declaration":true},"location":{"query":"logging.Function.logError","hash":""},"text":{},"parentId":5214}
