{"id":7269,"name":"DefaultNormalizerOptions","kind":256,"kindString":"Interface","flags":{"isExternal":true},"children":[{"id":7271,"name":"collapseWhitespace","kind":1024,"kindString":"Property","flags":{"isExternal":true,"isOptional":true},"sources":[{"fileName":"node_modules/@testing-library/dom/types/matches.d.ts","fullFileName":"/home/runner/work/FAIMS3/FAIMS3/node_modules/@testing-library/dom/types/matches.d.ts","line":39,"character":2}],"type":{"type":"intrinsic","name":"boolean"},"is":{"declaration":true},"location":{"query":"gui/fields/utils.Interface.DefaultNormalizerOptions","hash":"collapseWhitespace"},"text":{},"parentId":7269},{"id":7270,"name":"trim","kind":1024,"kindString":"Property","flags":{"isExternal":true,"isOptional":true},"sources":[{"fileName":"node_modules/@testing-library/dom/types/matches.d.ts","fullFileName":"/home/runner/work/FAIMS3/FAIMS3/node_modules/@testing-library/dom/types/matches.d.ts","line":38,"character":2}],"type":{"type":"intrinsic","name":"boolean"},"is":{"declaration":true},"location":{"query":"gui/fields/utils.Interface.DefaultNormalizerOptions","hash":"trim"},"text":{},"parentId":7269}],"groups":[{"title":"Properties","children":[7271,7270]}],"sources":[{"fileName":"node_modules/@testing-library/dom/types/matches.d.ts","fullFileName":"/home/runner/work/FAIMS3/FAIMS3/node_modules/@testing-library/dom/types/matches.d.ts","line":37,"character":17}],"extendedBy":[{"type":"reference","id":7252,"name":"NormalizerOptions"}],"is":{"declaration":true},"location":{"query":"gui/fields/utils.Interface.DefaultNormalizerOptions","hash":""},"text":{},"parentId":4924,"hierarchy":[{"name":"DefaultNormalizerOptions","isTarget":true,"linkId":"7269","children":[{"name":"NormalizerOptions","linkId":"7252"}]}]}
