{"id":7230,"name":"waitForElementToBeRemoved","kind":64,"kindString":"Function","flags":{"isExternal":true},"children":[],"sources":[{"fileName":"node_modules/@testing-library/dom/types/wait-for-element-to-be-removed.d.ts","fullFileName":"/home/brian/FAIMS/3/FAIMS3/node_modules/@testing-library/dom/types/wait-for-element-to-be-removed.d.ts","line":3,"character":16}],"signatures":[{"id":7231,"name":"waitForElementToBeRemoved","kind":4096,"kindString":"Call signature","flags":{"isExternal":true},"typeParameter":[{"id":7232,"name":"T","kind":131072,"kindString":"Type parameter","flags":{"isExternal":true}}],"parameters":[{"id":7233,"name":"callback","kind":32768,"kindString":"Parameter","flags":{"isExternal":true},"type":{"type":"union","types":[{"type":"reference","id":7232,"name":"T","qualifiedName":"T","package":"@testing-library/dom"},{"type":"reflection","declaration":{"id":7234,"name":"__type","kind":65536,"kindString":"Type literal","flags":{"isExternal":true},"sources":[{"fileName":"node_modules/@testing-library/dom/types/wait-for-element-to-be-removed.d.ts","line":4,"character":17}],"signatures":[{"id":7235,"name":"__type","kind":4096,"kindString":"Call signature","flags":{"isExternal":true},"type":{"type":"reference","id":7232,"name":"T","qualifiedName":"T","package":"@testing-library/dom"}}]}}]},"text":{}},{"id":7236,"name":"options","kind":32768,"kindString":"Parameter","flags":{"isExternal":true,"isOptional":true},"type":{"type":"reference","id":7221,"name":"waitForOptions","qualifiedName":"waitForOptions","package":"@testing-library/dom"},"text":{}}],"type":{"type":"reference","typeArguments":[{"type":"intrinsic","name":"void"}],"name":"Promise","qualifiedName":"Promise","package":"typescript"},"is":{"declaration":false},"location":{"query":"gui/fields/utils.Function.waitForElementToBeRemoved","hash":"waitForElementToBeRemoved"},"text":{},"sources":[{"fileName":"node_modules/@testing-library/dom/types/wait-for-element-to-be-removed.d.ts","fullFileName":"/home/brian/FAIMS/3/FAIMS3/node_modules/@testing-library/dom/types/wait-for-element-to-be-removed.d.ts","line":3,"character":0}],"parentId":7230}],"is":{"declaration":true},"location":{"query":"gui/fields/utils.Function.waitForElementToBeRemoved","hash":""},"text":{},"parentId":4924}
