{"id":406,"name":"set_local_autoincrement_ranges_for_field","kind":64,"kindString":"Function","flags":{},"children":[],"sources":[{"fileName":"src/datamodel/autoincrement.ts","fullFileName":"/home/brian/FAIMS/3/FAIMS3/src/datamodel/autoincrement.ts","line":123,"character":22,"url":"https://github.com/FAIMS/FAIMS3/blob/766d1cb2/src/datamodel/autoincrement.ts#L123"}],"signatures":[{"id":407,"name":"set_local_autoincrement_ranges_for_field","kind":4096,"kindString":"Call signature","flags":{},"parameters":[{"id":408,"name":"project_id","kind":32768,"kindString":"Parameter","flags":{},"type":{"type":"intrinsic","name":"string"},"text":{}},{"id":409,"name":"form_id","kind":32768,"kindString":"Parameter","flags":{},"type":{"type":"intrinsic","name":"string"},"text":{}},{"id":410,"name":"field_id","kind":32768,"kindString":"Parameter","flags":{},"type":{"type":"intrinsic","name":"string"},"text":{}},{"id":411,"name":"new_ranges","kind":32768,"kindString":"Parameter","flags":{},"type":{"type":"array","elementType":{"type":"reference","id":689,"name":"LocalAutoIncrementRange"}},"text":{}}],"type":{"type":"reference","typeArguments":[{"type":"intrinsic","name":"void"}],"name":"Promise","qualifiedName":"Promise","package":"typescript"},"is":{"declaration":false},"location":{"query":"datamodel/autoincrement.Function.set_local_autoincrement_ranges_for_field","hash":"set_local_autoincrement_ranges_for_field"},"text":{},"sources":[{"fileName":"src/datamodel/autoincrement.ts","fullFileName":"/home/brian/FAIMS/3/FAIMS3/src/datamodel/autoincrement.ts","line":123,"character":0,"url":"https://github.com/FAIMS/FAIMS3/blob/766d1cb2/src/datamodel/autoincrement.ts#L123"}],"parentId":406}],"is":{"declaration":true},"location":{"query":"datamodel/autoincrement.Function.set_local_autoincrement_ranges_for_field","hash":""},"text":{},"parentId":388}
